LICENSE
MANIFEST.in
README.md
setup.py
djson_field/__init__.py
djson_field/forms.py
djson_field/models.py
djson_field/tests.py
djson_field/views.py
djson_field/widgets.py
djson_field.egg-info/PKG-INFO
djson_field.egg-info/SOURCES.txt
djson_field.egg-info/dependency_links.txt
djson_field.egg-info/requires.txt
djson_field.egg-info/top_level.txt
djson_field/static/css/djson_field.css
djson_field/static/js/djson_field.js
djson_field/templates/djson_field/add_links.html
djson_field/templates/djson_field/base.html
djson_field/templates/djson_field/complex_field.html
djson_field/templates/djson_field/dictionary_item.html
djson_field/templates/djson_field/item_info.html
djson_field/templates/djson_field/item_templates.html
djson_field/templates/djson_field/list_item.html
djson_field/templates/djson_field/plain_item.html